boyd_bot/__init__.py
boyd_bot/__main__.py
boyd_bot/timetable.py
boyd_bot_glasgow-1.6.1.dist-info/LICENSE
boyd_bot_glasgow-1.6.1.dist-info/METADATA
boyd_bot_glasgow-1.6.1.dist-info/WHEEL
boyd_bot_glasgow-1.6.1.dist-info/entry_points.txt
boyd_bot_glasgow-1.6.1.dist-info/top_level.txt
boyd_bot_glasgow-1.6.1.dist-info/RECORD
