Metadata-Version: 2.1
Name: boyd-bot-glasgow
Version: 1.6.1
Summary: University Timetable on your Terminal!
Home-page: https://github.com/ineshbose/boyd_bot_terminal
Author: Inesh Bose
License: MIT
Keywords: glasgow university timetable
Platform: UNKNOWN
Requires-Dist: certifi (==2020.4.5.1)
Requires-Dist: chardet (==3.0.4)
Requires-Dist: fuzzywuzzy (==0.18.0)
Requires-Dist: icalendar (==4.0.6)
Requires-Dist: idna (==2.9)
Requires-Dist: keyring (==21.2.1)
Requires-Dist: python-Levenshtein-wheels (==0.13.1)
Requires-Dist: pytz (==2020.1)
Requires-Dist: requests (==2.23.0)
Requires-Dist: six (==1.15.0)
Requires-Dist: tzlocal (==2.1)
Requires-Dist: urllib3 (==1.25.9)
